bossimage/__init__.py
bossimage/cli.py
bossimage/core.py
bossimage/win-userdata.txt
bossimage-0.6.3.dist-info/METADATA
bossimage-0.6.3.dist-info/RECORD
bossimage-0.6.3.dist-info/WHEEL
bossimage-0.6.3.dist-info/entry_points.txt
bossimage-0.6.3.dist-info/top_level.txt
