Metadata-Version: 2.1
Name: bossimage
Version: 0.6.3
Summary: Tool to create AMIs with Ansible
Home-page: https://github.com/cloudboss/bossimage
Author: Joseph Wright
Author-email: joseph@cloudboss.co
License: UNKNOWN
Download-URL: https://pypi.python.org/pypi/friend
Platform: UNKNOWN
Requires-Dist: ansible
Requires-Dist: boto3
Requires-Dist: click
Requires-Dist: friend
Requires-Dist: pywinrm
Requires-Dist: voluptuous
